{"_path":"/fundamentals/utilities","_dir":"fundamentals","_draft":false,"_partial":false,"_locale":"","_empty":false,"title":"Utilities","description":"","body":{"type":"root","children":[{"type":"element","tag":"h1","props":{"id":"utilities-in-riotblossom"},"children":[{"type":"text","value":"Utilities in RiotBlossom"}]},{"type":"element","tag":"p","props":{},"children":[{"type":"text","value":"Public utilities are also offered for use in RiotBlossom!"}]},{"type":"element","tag":"p","props":{},"children":[{"type":"text","value":"Mappers and converters are included to get the raw or converted values of the aforementioned types in the previous section."}]},{"type":"element","tag":"p","props":{},"children":[{"type":"text","value":"These are used internally for projecting values when making requests to the Riot APIs."}]},{"type":"element","tag":"ul","props":{},"children":[{"type":"element","tag":"li","props":{},"children":[{"type":"element","tag":"code-inline","props":{},"children":[{"type":"text","value":"LeagueDivisionMapper"}]}]},{"type":"element","tag":"li","props":{},"children":[{"type":"element","tag":"code-inline","props":{},"children":[{"type":"text","value":"LeagueQueueMapper"}]}]},{"type":"element","tag":"li","props":{},"children":[{"type":"element","tag":"code-inline","props":{},"children":[{"type":"text","value":"LeagueTierMapper"}]}]},{"type":"element","tag":"li","props":{},"children":[{"type":"element","tag":"code-inline","props":{},"children":[{"type":"text","value":"LorRegionMapper"}]}]},{"type":"element","tag":"li","props":{},"children":[{"type":"element","tag":"code-inline","props":{},"children":[{"type":"text","value":"TftLeagueQueueMapper"}]}]},{"type":"element","tag":"li","props":{},"children":[{"type":"element","tag":"code-inline","props":{},"children":[{"type":"text","value":"PlatformMapper"}]}]},{"type":"element","tag":"li","props":{},"children":[{"type":"element","tag":"code-inline","props":{},"children":[{"type":"text","value":"PlatformToRegionConverter"}]}]},{"type":"element","tag":"li","props":{},"children":[{"type":"element","tag":"code-inline","props":{},"children":[{"type":"text","value":"PrettyPrinter"}]}]},{"type":"element","tag":"li","props":{},"children":[{"type":"element","tag":"code-inline","props":{},"children":[{"type":"text","value":"RegionMapper"}]}]},{"type":"element","tag":"li","props":{},"children":[{"type":"element","tag":"code-inline","props":{},"children":[{"type":"text","value":"ValRegionMapper"}]}]}]},{"type":"element","tag":"h2","props":{"id":"leaguedivisionmapper"},"children":[{"type":"text","value":"LeagueDivisionMapper"}]},{"type":"element","tag":"p","props":{},"children":[{"type":"text","value":"Maps a "},{"type":"element","tag":"code-inline","props":{},"children":[{"type":"text","value":"LeagueDivision"}]},{"type":"text","value":" enum to a string representation used for the Riot API."}]},{"type":"element","tag":"code","props":{"code":"// => \"I\"\nLeagueDivisionMapper.GetValue(LeagueDivision.I);\n","language":"csharp","meta":null},"children":[{"type":"element","tag":"pre","props":{},"children":[{"type":"element","tag":"code","props":{"__ignoreMap":""},"children":[{"type":"element","tag":"span","props":{"class":"line","line":1},"children":[{"type":"element","tag":"span","props":{"class":"ct-2c73f6"},"children":[{"type":"text","value":"// => \"I\"\n"}]}]},{"type":"element","tag":"span","props":{"class":"line","line":2},"children":[{"type":"element","tag":"span","props":{"class":"ct-288c45"},"children":[{"type":"text","value":"LeagueDivisionMapper."}]},{"type":"element","tag":"span","props":{"class":"ct-f604e1"},"children":[{"type":"text","value":"GetValue"}]},{"type":"element","tag":"span","props":{"class":"ct-288c45"},"children":[{"type":"text","value":"(LeagueDivision.I);"}]}]}]}]}]},{"type":"element","tag":"h2","props":{"id":"leaguequeuemapper"},"children":[{"type":"text","value":"LeagueQueueMapper"}]},{"type":"element","tag":"p","props":{},"children":[{"type":"text","value":"Maps a "},{"type":"element","tag":"code-inline","props":{},"children":[{"type":"text","value":"LeagueQueue"}]},{"type":"text","value":" enum to a string representation used for the Riot API."}]},{"type":"element","tag":"code","props":{"code":"// => \"RANKED_SOLO_5x5\"\nLeagueQueueMapper.GetValue(LeagueQueue.RankedSolo5x5);\n","language":"csharp","meta":null},"children":[{"type":"element","tag":"pre","props":{},"children":[{"type":"element","tag":"code","props":{"__ignoreMap":""},"children":[{"type":"element","tag":"span","props":{"class":"line","line":1},"children":[{"type":"element","tag":"span","props":{"class":"ct-2c73f6"},"children":[{"type":"text","value":"// => \"RANKED_SOLO_5x5\"\n"}]}]},{"type":"element","tag":"span","props":{"class":"line","line":2},"children":[{"type":"element","tag":"span","props":{"class":"ct-288c45"},"children":[{"type":"text","value":"LeagueQueueMapper."}]},{"type":"element","tag":"span","props":{"class":"ct-f604e1"},"children":[{"type":"text","value":"GetValue"}]},{"type":"element","tag":"span","props":{"class":"ct-288c45"},"children":[{"type":"text","value":"(LeagueQueue.RankedSolo5x5);"}]}]}]}]}]},{"type":"element","tag":"h2","props":{"id":"leaguetiermapper"},"children":[{"type":"text","value":"LeagueTierMapper"}]},{"type":"element","tag":"p","props":{},"children":[{"type":"text","value":"Maps a "},{"type":"element","tag":"code-inline","props":{},"children":[{"type":"text","value":"LeagueTier"}]},{"type":"text","value":" enum to a string representation used for the Riot API."}]},{"type":"element","tag":"code","props":{"code":"// => \"IRON\"\nLeagueTierMapper.GetValue(LeagueTier.Iron);\n","language":"csharp","meta":null},"children":[{"type":"element","tag":"pre","props":{},"children":[{"type":"element","tag":"code","props":{"__ignoreMap":""},"children":[{"type":"element","tag":"span","props":{"class":"line","line":1},"children":[{"type":"element","tag":"span","props":{"class":"ct-2c73f6"},"children":[{"type":"text","value":"// => \"IRON\"\n"}]}]},{"type":"element","tag":"span","props":{"class":"line","line":2},"children":[{"type":"element","tag":"span","props":{"class":"ct-288c45"},"children":[{"type":"text","value":"LeagueTierMapper."}]},{"type":"element","tag":"span","props":{"class":"ct-f604e1"},"children":[{"type":"text","value":"GetValue"}]},{"type":"element","tag":"span","props":{"class":"ct-288c45"},"children":[{"type":"text","value":"(LeagueTier.Iron);"}]}]}]}]}]},{"type":"element","tag":"h2","props":{"id":"lorregionmapper"},"children":[{"type":"text","value":"LorRegionMapper"}]},{"type":"element","tag":"p","props":{},"children":[{"type":"text","value":"Maps a "},{"type":"element","tag":"code-inline","props":{},"children":[{"type":"text","value":"LorRegion"}]},{"type":"text","value":" enum to a string representation used for the Riot API. Can also\nbe done the other way around!"}]},{"type":"element","tag":"code","props":{"code":"// => \"sea\"\nLorRegionMapper.GetId(LorRegion.SouthEastAsia);\n","language":"csharp","meta":null},"children":[{"type":"element","tag":"pre","props":{},"children":[{"type":"element","tag":"code","props":{"__ignoreMap":""},"children":[{"type":"element","tag":"span","props":{"class":"line","line":1},"children":[{"type":"element","tag":"span","props":{"class":"ct-2c73f6"},"children":[{"type":"text","value":"// => \"sea\"\n"}]}]},{"type":"element","tag":"span","props":{"class":"line","line":2},"children":[{"type":"element","tag":"span","props":{"class":"ct-288c45"},"children":[{"type":"text","value":"LorRegionMapper."}]},{"type":"element","tag":"span","props":{"class":"ct-f604e1"},"children":[{"type":"text","value":"GetId"}]},{"type":"element","tag":"span","props":{"class":"ct-288c45"},"children":[{"type":"text","value":"(LorRegion.SouthEastAsia);"}]}]}]}]}]},{"type":"element","tag":"code","props":{"code":"// => LorRegion.SouthEastAsia\nLorRegionMapper.FromId(\"sea\");\n","language":"csharp","meta":null},"children":[{"type":"element","tag":"pre","props":{},"children":[{"type":"element","tag":"code","props":{"__ignoreMap":""},"children":[{"type":"element","tag":"span","props":{"class":"line","line":1},"children":[{"type":"element","tag":"span","props":{"class":"ct-2c73f6"},"children":[{"type":"text","value":"// => LorRegion.SouthEastAsia\n"}]}]},{"type":"element","tag":"span","props":{"class":"line","line":2},"children":[{"type":"element","tag":"span","props":{"class":"ct-288c45"},"children":[{"type":"text","value":"LorRegionMapper."}]},{"type":"element","tag":"span","props":{"class":"ct-f604e1"},"children":[{"type":"text","value":"FromId"}]},{"type":"element","tag":"span","props":{"class":"ct-288c45"},"children":[{"type":"text","value":"("}]},{"type":"element","tag":"span","props":{"class":"ct-da067e"},"children":[{"type":"text","value":"\"sea\""}]},{"type":"element","tag":"span","props":{"class":"ct-288c45"},"children":[{"type":"text","value":");"}]}]}]}]}]},{"type":"element","tag":"h2","props":{"id":"tftleaguequeuemapper"},"children":[{"type":"text","value":"TftLeagueQueueMapper"}]},{"type":"element","tag":"p","props":{},"children":[{"type":"text","value":"Maps a "},{"type":"element","tag":"code-inline","props":{},"children":[{"type":"text","value":"TftLeagueQueue"}]},{"type":"text","value":" enum to a string representation used for the Riot API."}]},{"type":"element","tag":"code","props":{"code":"// => \"RANKED_TFT_TURBO\"\nTftLeagueQueueMapper.GetValue(TftLeagueQueue.RankedTftTurbo);\n","language":"csharp","meta":null},"children":[{"type":"element","tag":"pre","props":{},"children":[{"type":"element","tag":"code","props":{"__ignoreMap":""},"children":[{"type":"element","tag":"span","props":{"class":"line","line":1},"children":[{"type":"element","tag":"span","props":{"class":"ct-2c73f6"},"children":[{"type":"text","value":"// => \"RANKED_TFT_TURBO\"\n"}]}]},{"type":"element","tag":"span","props":{"class":"line","line":2},"children":[{"type":"element","tag":"span","props":{"class":"ct-288c45"},"children":[{"type":"text","value":"TftLeagueQueueMapper."}]},{"type":"element","tag":"span","props":{"class":"ct-f604e1"},"children":[{"type":"text","value":"GetValue"}]},{"type":"element","tag":"span","props":{"class":"ct-288c45"},"children":[{"type":"text","value":"(TftLeagueQueue.RankedTftTurbo);"}]}]}]}]}]},{"type":"element","tag":"h2","props":{"id":"platformmapper"},"children":[{"type":"text","value":"PlatformMapper"}]},{"type":"element","tag":"p","props":{},"children":[{"type":"text","value":"Maps a "},{"type":"element","tag":"code-inline","props":{},"children":[{"type":"text","value":"Platform"}]},{"type":"text","value":" enum to a string representation used for the Riot API. Can also\nbe done the other way around!"}]},{"type":"element","tag":"code","props":{"code":"// => \"na1\"\nPlatformMapper.GetId(Platform.NorthAmerica);\n","language":"csharp","meta":null},"children":[{"type":"element","tag":"pre","props":{},"children":[{"type":"element","tag":"code","props":{"__ignoreMap":""},"children":[{"type":"element","tag":"span","props":{"class":"line","line":1},"children":[{"type":"element","tag":"span","props":{"class":"ct-2c73f6"},"children":[{"type":"text","value":"// => \"na1\"\n"}]}]},{"type":"element","tag":"span","props":{"class":"line","line":2},"children":[{"type":"element","tag":"span","props":{"class":"ct-288c45"},"children":[{"type":"text","value":"PlatformMapper."}]},{"type":"element","tag":"span","props":{"class":"ct-f604e1"},"children":[{"type":"text","value":"GetId"}]},{"type":"element","tag":"span","props":{"class":"ct-288c45"},"children":[{"type":"text","value":"(Platform.NorthAmerica);"}]}]}]}]}]},{"type":"element","tag":"code","props":{"code":"// => Platform.Japan\nPlatformMapper.FromId(\"jp1\");\n","language":"csharp","meta":null},"children":[{"type":"element","tag":"pre","props":{},"children":[{"type":"element","tag":"code","props":{"__ignoreMap":""},"children":[{"type":"element","tag":"span","props":{"class":"line","line":1},"children":[{"type":"element","tag":"span","props":{"class":"ct-2c73f6"},"children":[{"type":"text","value":"// => Platform.Japan\n"}]}]},{"type":"element","tag":"span","props":{"class":"line","line":2},"children":[{"type":"element","tag":"span","props":{"class":"ct-288c45"},"children":[{"type":"text","value":"PlatformMapper."}]},{"type":"element","tag":"span","props":{"class":"ct-f604e1"},"children":[{"type":"text","value":"FromId"}]},{"type":"element","tag":"span","props":{"class":"ct-288c45"},"children":[{"type":"text","value":"("}]},{"type":"element","tag":"span","props":{"class":"ct-da067e"},"children":[{"type":"text","value":"\"jp1\""}]},{"type":"element","tag":"span","props":{"class":"ct-288c45"},"children":[{"type":"text","value":");"}]}]}]}]}]},{"type":"element","tag":"h2","props":{"id":"platformtoregionconverter"},"children":[{"type":"text","value":"PlatformToRegionConverter"}]},{"type":"element","tag":"p","props":{},"children":[{"type":"text","value":"Converter for the "},{"type":"element","tag":"code-inline","props":{},"children":[{"type":"text","value":"Platform"}]},{"type":"text","value":" and "},{"type":"element","tag":"code-inline","props":{},"children":[{"type":"text","value":"Region"}]},{"type":"text","value":" enums."}]},{"type":"element","tag":"code","props":{"code":"// => Region.Americas\nPlatformToRegionConverter.ToRegion(Platform.NorthAmerica);\n","language":"csharp","meta":null},"children":[{"type":"element","tag":"pre","props":{},"children":[{"type":"element","tag":"code","props":{"__ignoreMap":""},"children":[{"type":"element","tag":"span","props":{"class":"line","line":1},"children":[{"type":"element","tag":"span","props":{"class":"ct-2c73f6"},"children":[{"type":"text","value":"// => Region.Americas\n"}]}]},{"type":"element","tag":"span","props":{"class":"line","line":2},"children":[{"type":"element","tag":"span","props":{"class":"ct-288c45"},"children":[{"type":"text","value":"PlatformToRegionConverter."}]},{"type":"element","tag":"span","props":{"class":"ct-f604e1"},"children":[{"type":"text","value":"ToRegion"}]},{"type":"element","tag":"span","props":{"class":"ct-288c45"},"children":[{"type":"text","value":"(Platform.NorthAmerica);"}]}]}]}]}]},{"type":"element","tag":"h2","props":{"id":"prettyprinter"},"children":[{"type":"text","value":"PrettyPrinter"}]},{"type":"element","tag":"p","props":{},"children":[{"type":"text","value":"Generates a pretty string representation of a data object. This is used for all\n"},{"type":"element","tag":"strong","props":{},"children":[{"type":"text","value":"data transfer objects"}]},{"type":"text","value":" served by RiotBlossom! :3"}]},{"type":"element","tag":"p","props":{},"children":[{"type":"element","tag":"code-inline","props":{},"children":[{"type":"text","value":"PrettyPrinter"}]},{"type":"text","value":" is useful for printing objects from the "},{"type":"element","tag":"code-inline","props":{},"children":[{"type":"text","value":"System.Collections"}]},{"type":"text","value":" namespace.\nLook at how pretty it is!!! :3"}]},{"type":"element","tag":"code","props":{"code":"var itemDictionary = await client.CommunityDragon.GetItemDictionaryAsync();\nstring pp = PrettyPrinter.GetString(itemDictionary);\nConsole.WriteLine(pp);\n","language":"csharp","meta":null},"children":[{"type":"element","tag":"pre","props":{},"children":[{"type":"element","tag":"code","props":{"__ignoreMap":""},"children":[{"type":"element","tag":"span","props":{"class":"line","line":1},"children":[{"type":"element","tag":"span","props":{"class":"ct-8712d5"},"children":[{"type":"text","value":"var"}]},{"type":"element","tag":"span","props":{"class":"ct-288c45"},"children":[{"type":"text","value":" "}]},{"type":"element","tag":"span","props":{"class":"ct-81bc0b"},"children":[{"type":"text","value":"itemDictionary"}]},{"type":"element","tag":"span","props":{"class":"ct-288c45"},"children":[{"type":"text","value":" "}]},{"type":"element","tag":"span","props":{"class":"ct-8712d5"},"children":[{"type":"text","value":"="}]},{"type":"element","tag":"span","props":{"class":"ct-288c45"},"children":[{"type":"text","value":" "}]},{"type":"element","tag":"span","props":{"class":"ct-8712d5"},"children":[{"type":"text","value":"await"}]},{"type":"element","tag":"span","props":{"class":"ct-288c45"},"children":[{"type":"text","value":" client.CommunityDragon."}]},{"type":"element","tag":"span","props":{"class":"ct-f604e1"},"children":[{"type":"text","value":"GetItemDictionaryAsync"}]},{"type":"element","tag":"span","props":{"class":"ct-288c45"},"children":[{"type":"text","value":"();\n"}]}]},{"type":"element","tag":"span","props":{"class":"line","line":2},"children":[{"type":"element","tag":"span","props":{"class":"ct-8712d5"},"children":[{"type":"text","value":"string"}]},{"type":"element","tag":"span","props":{"class":"ct-288c45"},"children":[{"type":"text","value":" "}]},{"type":"element","tag":"span","props":{"class":"ct-81bc0b"},"children":[{"type":"text","value":"pp"}]},{"type":"element","tag":"span","props":{"class":"ct-288c45"},"children":[{"type":"text","value":" "}]},{"type":"element","tag":"span","props":{"class":"ct-8712d5"},"children":[{"type":"text","value":"="}]},{"type":"element","tag":"span","props":{"class":"ct-288c45"},"children":[{"type":"text","value":" PrettyPrinter."}]},{"type":"element","tag":"span","props":{"class":"ct-f604e1"},"children":[{"type":"text","value":"GetString"}]},{"type":"element","tag":"span","props":{"class":"ct-288c45"},"children":[{"type":"text","value":"(itemDictionary);\n"}]}]},{"type":"element","tag":"span","props":{"class":"line","line":3},"children":[{"type":"element","tag":"span","props":{"class":"ct-288c45"},"children":[{"type":"text","value":"Console."}]},{"type":"element","tag":"span","props":{"class":"ct-f604e1"},"children":[{"type":"text","value":"WriteLine"}]},{"type":"element","tag":"span","props":{"class":"ct-288c45"},"children":[{"type":"text","value":"(pp);"}]}]}]}]}]},{"type":"element","tag":"code","props":{"code":"IEnumerable`1[KeyValuePair`2] [\n  {\n    \"Key\": 1001,\n    \"Value\": {\n      \"Id\": 1001,\n      \"Name\": \"Boots\",\n      \"Description\": \"<mainText><stats><attention> 25</attention> Move Speed</stats></mainText><br>\",\n      \"Active\": false,\n      \"InStore\": true,\n      \"From\": [],\n      \"To\": [\n        3111,\n        3006,\n        3009,\n        3020,\n        3047,\n        3117,\n        3158\n      ],\n      \"Categories\": [\n        \"Boots\"\n      ],\n      \"MaxStacks\": 1,\n      \"RequiredChampion\": \"\",\n      \"RequiredAlly\": \"\",\n      \"RequiredBuffCurrencyName\": \"\",\n      \"RequiredBuffCurrencyCost\": 0,\n      \"SpecialRecipe\": 0,\n      \"IsEnchantment\": false,\n      \"Price\": 300,\n      \"PriceTotal\": 300,\n      \"IconPath\": \"/lol-game-data/assets/ASSETS/Items/Icons2D/1001_Class_T1_BootsofSpeed.png\"\n    }\n  }\n]\n","language":"json","meta":null},"children":[{"type":"element","tag":"pre","props":{},"children":[{"type":"element","tag":"code","props":{"__ignoreMap":""},"children":[{"type":"element","tag":"span","props":{"class":"line","line":1},"children":[{"type":"element","tag":"span","props":{"class":"ct-288c45"},"children":[{"type":"text","value":"IEnumerable`"}]},{"type":"element","tag":"span","props":{"class":"ct-1f7ce8"},"children":[{"type":"text","value":"1"}]},{"type":"element","tag":"span","props":{"class":"ct-288c45"},"children":[{"type":"text","value":"["}]},{"type":"element","tag":"span","props":{"class":"ct-37dcf1"},"children":[{"type":"text","value":"KeyValuePair`"}]},{"type":"element","tag":"span","props":{"class":"ct-1f7ce8"},"children":[{"type":"text","value":"2"}]},{"type":"element","tag":"span","props":{"class":"ct-288c45"},"children":[{"type":"text","value":"] [\n"}]}]},{"type":"element","tag":"span","props":{"class":"line","line":2},"children":[{"type":"element","tag":"span","props":{"class":"ct-288c45"},"children":[{"type":"text","value":"  {\n"}]}]},{"type":"element","tag":"span","props":{"class":"line","line":3},"children":[{"type":"element","tag":"span","props":{"class":"ct-288c45"},"children":[{"type":"text","value":"    "}]},{"type":"element","tag":"span","props":{"class":"ct-245334"},"children":[{"type":"text","value":"\"Key\""}]},{"type":"element","tag":"span","props":{"class":"ct-288c45"},"children":[{"type":"text","value":": "}]},{"type":"element","tag":"span","props":{"class":"ct-1f7ce8"},"children":[{"type":"text","value":"1001"}]},{"type":"element","tag":"span","props":{"class":"ct-288c45"},"children":[{"type":"text","value":",\n"}]}]},{"type":"element","tag":"span","props":{"class":"line","line":4},"children":[{"type":"element","tag":"span","props":{"class":"ct-288c45"},"children":[{"type":"text","value":"    "}]},{"type":"element","tag":"span","props":{"class":"ct-245334"},"children":[{"type":"text","value":"\"Value\""}]},{"type":"element","tag":"span","props":{"class":"ct-288c45"},"children":[{"type":"text","value":": {\n"}]}]},{"type":"element","tag":"span","props":{"class":"line","line":5},"children":[{"type":"element","tag":"span","props":{"class":"ct-288c45"},"children":[{"type":"text","value":"      "}]},{"type":"element","tag":"span","props":{"class":"ct-245334"},"children":[{"type":"text","value":"\"Id\""}]},{"type":"element","tag":"span","props":{"class":"ct-288c45"},"children":[{"type":"text","value":": "}]},{"type":"element","tag":"span","props":{"class":"ct-1f7ce8"},"children":[{"type":"text","value":"1001"}]},{"type":"element","tag":"span","props":{"class":"ct-288c45"},"children":[{"type":"text","value":",\n"}]}]},{"type":"element","tag":"span","props":{"class":"line","line":6},"children":[{"type":"element","tag":"span","props":{"class":"ct-288c45"},"children":[{"type":"text","value":"      "}]},{"type":"element","tag":"span","props":{"class":"ct-245334"},"children":[{"type":"text","value":"\"Name\""}]},{"type":"element","tag":"span","props":{"class":"ct-288c45"},"children":[{"type":"text","value":": "}]},{"type":"element","tag":"span","props":{"class":"ct-da067e"},"children":[{"type":"text","value":"\"Boots\""}]},{"type":"element","tag":"span","props":{"class":"ct-288c45"},"children":[{"type":"text","value":",\n"}]}]},{"type":"element","tag":"span","props":{"class":"line","line":7},"children":[{"type":"element","tag":"span","props":{"class":"ct-288c45"},"children":[{"type":"text","value":"      "}]},{"type":"element","tag":"span","props":{"class":"ct-245334"},"children":[{"type":"text","value":"\"Description\""}]},{"type":"element","tag":"span","props":{"class":"ct-288c45"},"children":[{"type":"text","value":": "}]},{"type":"element","tag":"span","props":{"class":"ct-da067e"},"children":[{"type":"text","value":"\"<mainText><stats><attention> 25</attention> Move Speed</stats></mainText><br>\""}]},{"type":"element","tag":"span","props":{"class":"ct-288c45"},"children":[{"type":"text","value":",\n"}]}]},{"type":"element","tag":"span","props":{"class":"line","line":8},"children":[{"type":"element","tag":"span","props":{"class":"ct-288c45"},"children":[{"type":"text","value":"      "}]},{"type":"element","tag":"span","props":{"class":"ct-245334"},"children":[{"type":"text","value":"\"Active\""}]},{"type":"element","tag":"span","props":{"class":"ct-288c45"},"children":[{"type":"text","value":": "}]},{"type":"element","tag":"span","props":{"class":"ct-1f7ce8"},"children":[{"type":"text","value":"false"}]},{"type":"element","tag":"span","props":{"class":"ct-288c45"},"children":[{"type":"text","value":",\n"}]}]},{"type":"element","tag":"span","props":{"class":"line","line":9},"children":[{"type":"element","tag":"span","props":{"class":"ct-288c45"},"children":[{"type":"text","value":"      "}]},{"type":"element","tag":"span","props":{"class":"ct-245334"},"children":[{"type":"text","value":"\"InStore\""}]},{"type":"element","tag":"span","props":{"class":"ct-288c45"},"children":[{"type":"text","value":": "}]},{"type":"element","tag":"span","props":{"class":"ct-1f7ce8"},"children":[{"type":"text","value":"true"}]},{"type":"element","tag":"span","props":{"class":"ct-288c45"},"children":[{"type":"text","value":",\n"}]}]},{"type":"element","tag":"span","props":{"class":"line","line":10},"children":[{"type":"element","tag":"span","props":{"class":"ct-288c45"},"children":[{"type":"text","value":"      "}]},{"type":"element","tag":"span","props":{"class":"ct-245334"},"children":[{"type":"text","value":"\"From\""}]},{"type":"element","tag":"span","props":{"class":"ct-288c45"},"children":[{"type":"text","value":": [],\n"}]}]},{"type":"element","tag":"span","props":{"class":"line","line":11},"children":[{"type":"element","tag":"span","props":{"class":"ct-288c45"},"children":[{"type":"text","value":"      "}]},{"type":"element","tag":"span","props":{"class":"ct-245334"},"children":[{"type":"text","value":"\"To\""}]},{"type":"element","tag":"span","props":{"class":"ct-288c45"},"children":[{"type":"text","value":": [\n"}]}]},{"type":"element","tag":"span","props":{"class":"line","line":12},"children":[{"type":"element","tag":"span","props":{"class":"ct-288c45"},"children":[{"type":"text","value":"        "}]},{"type":"element","tag":"span","props":{"class":"ct-1f7ce8"},"children":[{"type":"text","value":"3111"}]},{"type":"element","tag":"span","props":{"class":"ct-288c45"},"children":[{"type":"text","value":",\n"}]}]},{"type":"element","tag":"span","props":{"class":"line","line":13},"children":[{"type":"element","tag":"span","props":{"class":"ct-288c45"},"children":[{"type":"text","value":"        "}]},{"type":"element","tag":"span","props":{"class":"ct-1f7ce8"},"children":[{"type":"text","value":"3006"}]},{"type":"element","tag":"span","props":{"class":"ct-288c45"},"children":[{"type":"text","value":",\n"}]}]},{"type":"element","tag":"span","props":{"class":"line","line":14},"children":[{"type":"element","tag":"span","props":{"class":"ct-288c45"},"children":[{"type":"text","value":"        "}]},{"type":"element","tag":"span","props":{"class":"ct-1f7ce8"},"children":[{"type":"text","value":"3009"}]},{"type":"element","tag":"span","props":{"class":"ct-288c45"},"children":[{"type":"text","value":",\n"}]}]},{"type":"element","tag":"span","props":{"class":"line","line":15},"children":[{"type":"element","tag":"span","props":{"class":"ct-288c45"},"children":[{"type":"text","value":"        "}]},{"type":"element","tag":"span","props":{"class":"ct-1f7ce8"},"children":[{"type":"text","value":"3020"}]},{"type":"element","tag":"span","props":{"class":"ct-288c45"},"children":[{"type":"text","value":",\n"}]}]},{"type":"element","tag":"span","props":{"class":"line","line":16},"children":[{"type":"element","tag":"span","props":{"class":"ct-288c45"},"children":[{"type":"text","value":"        "}]},{"type":"element","tag":"span","props":{"class":"ct-1f7ce8"},"children":[{"type":"text","value":"3047"}]},{"type":"element","tag":"span","props":{"class":"ct-288c45"},"children":[{"type":"text","value":",\n"}]}]},{"type":"element","tag":"span","props":{"class":"line","line":17},"children":[{"type":"element","tag":"span","props":{"class":"ct-288c45"},"children":[{"type":"text","value":"        "}]},{"type":"element","tag":"span","props":{"class":"ct-1f7ce8"},"children":[{"type":"text","value":"3117"}]},{"type":"element","tag":"span","props":{"class":"ct-288c45"},"children":[{"type":"text","value":",\n"}]}]},{"type":"element","tag":"span","props":{"class":"line","line":18},"children":[{"type":"element","tag":"span","props":{"class":"ct-288c45"},"children":[{"type":"text","value":"        "}]},{"type":"element","tag":"span","props":{"class":"ct-1f7ce8"},"children":[{"type":"text","value":"3158\n"}]}]},{"type":"element","tag":"span","props":{"class":"line","line":19},"children":[{"type":"element","tag":"span","props":{"class":"ct-288c45"},"children":[{"type":"text","value":"      ],\n"}]}]},{"type":"element","tag":"span","props":{"class":"line","line":20},"children":[{"type":"element","tag":"span","props":{"class":"ct-288c45"},"children":[{"type":"text","value":"      "}]},{"type":"element","tag":"span","props":{"class":"ct-245334"},"children":[{"type":"text","value":"\"Categories\""}]},{"type":"element","tag":"span","props":{"class":"ct-288c45"},"children":[{"type":"text","value":": [\n"}]}]},{"type":"element","tag":"span","props":{"class":"line","line":21},"children":[{"type":"element","tag":"span","props":{"class":"ct-288c45"},"children":[{"type":"text","value":"        "}]},{"type":"element","tag":"span","props":{"class":"ct-da067e"},"children":[{"type":"text","value":"\"Boots\"\n"}]}]},{"type":"element","tag":"span","props":{"class":"line","line":22},"children":[{"type":"element","tag":"span","props":{"class":"ct-288c45"},"children":[{"type":"text","value":"      ],\n"}]}]},{"type":"element","tag":"span","props":{"class":"line","line":23},"children":[{"type":"element","tag":"span","props":{"class":"ct-288c45"},"children":[{"type":"text","value":"      "}]},{"type":"element","tag":"span","props":{"class":"ct-245334"},"children":[{"type":"text","value":"\"MaxStacks\""}]},{"type":"element","tag":"span","props":{"class":"ct-288c45"},"children":[{"type":"text","value":": "}]},{"type":"element","tag":"span","props":{"class":"ct-1f7ce8"},"children":[{"type":"text","value":"1"}]},{"type":"element","tag":"span","props":{"class":"ct-288c45"},"children":[{"type":"text","value":",\n"}]}]},{"type":"element","tag":"span","props":{"class":"line","line":24},"children":[{"type":"element","tag":"span","props":{"class":"ct-288c45"},"children":[{"type":"text","value":"      "}]},{"type":"element","tag":"span","props":{"class":"ct-245334"},"children":[{"type":"text","value":"\"RequiredChampion\""}]},{"type":"element","tag":"span","props":{"class":"ct-288c45"},"children":[{"type":"text","value":": "}]},{"type":"element","tag":"span","props":{"class":"ct-da067e"},"children":[{"type":"text","value":"\"\""}]},{"type":"element","tag":"span","props":{"class":"ct-288c45"},"children":[{"type":"text","value":",\n"}]}]},{"type":"element","tag":"span","props":{"class":"line","line":25},"children":[{"type":"element","tag":"span","props":{"class":"ct-288c45"},"children":[{"type":"text","value":"      "}]},{"type":"element","tag":"span","props":{"class":"ct-245334"},"children":[{"type":"text","value":"\"RequiredAlly\""}]},{"type":"element","tag":"span","props":{"class":"ct-288c45"},"children":[{"type":"text","value":": "}]},{"type":"element","tag":"span","props":{"class":"ct-da067e"},"children":[{"type":"text","value":"\"\""}]},{"type":"element","tag":"span","props":{"class":"ct-288c45"},"children":[{"type":"text","value":",\n"}]}]},{"type":"element","tag":"span","props":{"class":"line","line":26},"children":[{"type":"element","tag":"span","props":{"class":"ct-288c45"},"children":[{"type":"text","value":"      "}]},{"type":"element","tag":"span","props":{"class":"ct-245334"},"children":[{"type":"text","value":"\"RequiredBuffCurrencyName\""}]},{"type":"element","tag":"span","props":{"class":"ct-288c45"},"children":[{"type":"text","value":": "}]},{"type":"element","tag":"span","props":{"class":"ct-da067e"},"children":[{"type":"text","value":"\"\""}]},{"type":"element","tag":"span","props":{"class":"ct-288c45"},"children":[{"type":"text","value":",\n"}]}]},{"type":"element","tag":"span","props":{"class":"line","line":27},"children":[{"type":"element","tag":"span","props":{"class":"ct-288c45"},"children":[{"type":"text","value":"      "}]},{"type":"element","tag":"span","props":{"class":"ct-245334"},"children":[{"type":"text","value":"\"RequiredBuffCurrencyCost\""}]},{"type":"element","tag":"span","props":{"class":"ct-288c45"},"children":[{"type":"text","value":": "}]},{"type":"element","tag":"span","props":{"class":"ct-1f7ce8"},"children":[{"type":"text","value":"0"}]},{"type":"element","tag":"span","props":{"class":"ct-288c45"},"children":[{"type":"text","value":",\n"}]}]},{"type":"element","tag":"span","props":{"class":"line","line":28},"children":[{"type":"element","tag":"span","props":{"class":"ct-288c45"},"children":[{"type":"text","value":"      "}]},{"type":"element","tag":"span","props":{"class":"ct-245334"},"children":[{"type":"text","value":"\"SpecialRecipe\""}]},{"type":"element","tag":"span","props":{"class":"ct-288c45"},"children":[{"type":"text","value":": "}]},{"type":"element","tag":"span","props":{"class":"ct-1f7ce8"},"children":[{"type":"text","value":"0"}]},{"type":"element","tag":"span","props":{"class":"ct-288c45"},"children":[{"type":"text","value":",\n"}]}]},{"type":"element","tag":"span","props":{"class":"line","line":29},"children":[{"type":"element","tag":"span","props":{"class":"ct-288c45"},"children":[{"type":"text","value":"      "}]},{"type":"element","tag":"span","props":{"class":"ct-245334"},"children":[{"type":"text","value":"\"IsEnchantment\""}]},{"type":"element","tag":"span","props":{"class":"ct-288c45"},"children":[{"type":"text","value":": "}]},{"type":"element","tag":"span","props":{"class":"ct-1f7ce8"},"children":[{"type":"text","value":"false"}]},{"type":"element","tag":"span","props":{"class":"ct-288c45"},"children":[{"type":"text","value":",\n"}]}]},{"type":"element","tag":"span","props":{"class":"line","line":30},"children":[{"type":"element","tag":"span","props":{"class":"ct-288c45"},"children":[{"type":"text","value":"      "}]},{"type":"element","tag":"span","props":{"class":"ct-245334"},"children":[{"type":"text","value":"\"Price\""}]},{"type":"element","tag":"span","props":{"class":"ct-288c45"},"children":[{"type":"text","value":": "}]},{"type":"element","tag":"span","props":{"class":"ct-1f7ce8"},"children":[{"type":"text","value":"300"}]},{"type":"element","tag":"span","props":{"class":"ct-288c45"},"children":[{"type":"text","value":",\n"}]}]},{"type":"element","tag":"span","props":{"class":"line","line":31},"children":[{"type":"element","tag":"span","props":{"class":"ct-288c45"},"children":[{"type":"text","value":"      "}]},{"type":"element","tag":"span","props":{"class":"ct-245334"},"children":[{"type":"text","value":"\"PriceTotal\""}]},{"type":"element","tag":"span","props":{"class":"ct-288c45"},"children":[{"type":"text","value":": "}]},{"type":"element","tag":"span","props":{"class":"ct-1f7ce8"},"children":[{"type":"text","value":"300"}]},{"type":"element","tag":"span","props":{"class":"ct-288c45"},"children":[{"type":"text","value":",\n"}]}]},{"type":"element","tag":"span","props":{"class":"line","line":32},"children":[{"type":"element","tag":"span","props":{"class":"ct-288c45"},"children":[{"type":"text","value":"      "}]},{"type":"element","tag":"span","props":{"class":"ct-245334"},"children":[{"type":"text","value":"\"IconPath\""}]},{"type":"element","tag":"span","props":{"class":"ct-288c45"},"children":[{"type":"text","value":": "}]},{"type":"element","tag":"span","props":{"class":"ct-da067e"},"children":[{"type":"text","value":"\"/lol-game-data/assets/ASSETS/Items/Icons2D/1001_Class_T1_BootsofSpeed.png\"\n"}]}]},{"type":"element","tag":"span","props":{"class":"line","line":33},"children":[{"type":"element","tag":"span","props":{"class":"ct-288c45"},"children":[{"type":"text","value":"    }\n"}]}]},{"type":"element","tag":"span","props":{"class":"line","line":34},"children":[{"type":"element","tag":"span","props":{"class":"ct-288c45"},"children":[{"type":"text","value":"  }\n"}]}]},{"type":"element","tag":"span","props":{"class":"line","line":35},"children":[{"type":"element","tag":"span","props":{"class":"ct-288c45"},"children":[{"type":"text","value":"]"}]}]}]}]}]},{"type":"element","tag":"p","props":{},"children":[{"type":"text","value":"There is also a method overload that allows you to set the type label prefix! <3"}]},{"type":"element","tag":"code","props":{"code":"PrettyPrinter.GetString(itemDictionary, \"Items\")\n","language":"csharp","meta":null},"children":[{"type":"element","tag":"pre","props":{},"children":[{"type":"element","tag":"code","props":{"__ignoreMap":""},"children":[{"type":"element","tag":"span","props":{"class":"line","line":1},"children":[{"type":"element","tag":"span","props":{"class":"ct-288c45"},"children":[{"type":"text","value":"PrettyPrinter."}]},{"type":"element","tag":"span","props":{"class":"ct-f604e1"},"children":[{"type":"text","value":"GetString"}]},{"type":"element","tag":"span","props":{"class":"ct-288c45"},"children":[{"type":"text","value":"(itemDictionary, "}]},{"type":"element","tag":"span","props":{"class":"ct-da067e"},"children":[{"type":"text","value":"\"Items\""}]},{"type":"element","tag":"span","props":{"class":"ct-288c45"},"children":[{"type":"text","value":")"}]}]}]}]}]},{"type":"element","tag":"h2","props":{"id":"regionmapper"},"children":[{"type":"text","value":"RegionMapper"}]},{"type":"element","tag":"p","props":{},"children":[{"type":"text","value":"Maps a "},{"type":"element","tag":"code-inline","props":{},"children":[{"type":"text","value":"Region"}]},{"type":"text","value":" enum to a string representation used for the Riot API. Can also be\nused the other way around!"}]},{"type":"element","tag":"code","props":{"code":"// => \"sea\"\nRegionMapper.GetId(Region.SouthEastAsia);\n","language":"csharp","meta":null},"children":[{"type":"element","tag":"pre","props":{},"children":[{"type":"element","tag":"code","props":{"__ignoreMap":""},"children":[{"type":"element","tag":"span","props":{"class":"line","line":1},"children":[{"type":"element","tag":"span","props":{"class":"ct-2c73f6"},"children":[{"type":"text","value":"// => \"sea\"\n"}]}]},{"type":"element","tag":"span","props":{"class":"line","line":2},"children":[{"type":"element","tag":"span","props":{"class":"ct-288c45"},"children":[{"type":"text","value":"RegionMapper."}]},{"type":"element","tag":"span","props":{"class":"ct-f604e1"},"children":[{"type":"text","value":"GetId"}]},{"type":"element","tag":"span","props":{"class":"ct-288c45"},"children":[{"type":"text","value":"(Region.SouthEastAsia);"}]}]}]}]}]},{"type":"element","tag":"code","props":{"code":"// => Region.Asia\nRegionMapper.FromId(\"asia\");\n","language":"csharp","meta":null},"children":[{"type":"element","tag":"pre","props":{},"children":[{"type":"element","tag":"code","props":{"__ignoreMap":""},"children":[{"type":"element","tag":"span","props":{"class":"line","line":1},"children":[{"type":"element","tag":"span","props":{"class":"ct-2c73f6"},"children":[{"type":"text","value":"// => Region.Asia\n"}]}]},{"type":"element","tag":"span","props":{"class":"line","line":2},"children":[{"type":"element","tag":"span","props":{"class":"ct-288c45"},"children":[{"type":"text","value":"RegionMapper."}]},{"type":"element","tag":"span","props":{"class":"ct-f604e1"},"children":[{"type":"text","value":"FromId"}]},{"type":"element","tag":"span","props":{"class":"ct-288c45"},"children":[{"type":"text","value":"("}]},{"type":"element","tag":"span","props":{"class":"ct-da067e"},"children":[{"type":"text","value":"\"asia\""}]},{"type":"element","tag":"span","props":{"class":"ct-288c45"},"children":[{"type":"text","value":");"}]}]}]}]}]},{"type":"element","tag":"h2","props":{"id":"valregionmapper"},"children":[{"type":"text","value":"ValRegionMapper"}]},{"type":"element","tag":"p","props":{},"children":[{"type":"text","value":"Maps a "},{"type":"element","tag":"code-inline","props":{},"children":[{"type":"text","value":"ValRegion"}]},{"type":"text","value":" enum to a string representation used for the Riot API. Can also be\nused the other way around!"}]},{"type":"element","tag":"code","props":{"code":"// => \"ap\"\nValRegionMapper.GetId(ValRegion.AsiaPacific);\n","language":"csharp","meta":null},"children":[{"type":"element","tag":"pre","props":{},"children":[{"type":"element","tag":"code","props":{"__ignoreMap":""},"children":[{"type":"element","tag":"span","props":{"class":"line","line":1},"children":[{"type":"element","tag":"span","props":{"class":"ct-2c73f6"},"children":[{"type":"text","value":"// => \"ap\"\n"}]}]},{"type":"element","tag":"span","props":{"class":"line","line":2},"children":[{"type":"element","tag":"span","props":{"class":"ct-288c45"},"children":[{"type":"text","value":"ValRegionMapper."}]},{"type":"element","tag":"span","props":{"class":"ct-f604e1"},"children":[{"type":"text","value":"GetId"}]},{"type":"element","tag":"span","props":{"class":"ct-288c45"},"children":[{"type":"text","value":"(ValRegion.AsiaPacific);"}]}]}]}]}]},{"type":"element","tag":"code","props":{"code":"// => ValRegion.LatinAmerica\nValRegionMapper.FromId(\"latam\");\n","language":"csharp","meta":null},"children":[{"type":"element","tag":"pre","props":{},"children":[{"type":"element","tag":"code","props":{"__ignoreMap":""},"children":[{"type":"element","tag":"span","props":{"class":"line","line":1},"children":[{"type":"element","tag":"span","props":{"class":"ct-2c73f6"},"children":[{"type":"text","value":"// => ValRegion.LatinAmerica\n"}]}]},{"type":"element","tag":"span","props":{"class":"line","line":2},"children":[{"type":"element","tag":"span","props":{"class":"ct-288c45"},"children":[{"type":"text","value":"ValRegionMapper."}]},{"type":"element","tag":"span","props":{"class":"ct-f604e1"},"children":[{"type":"text","value":"FromId"}]},{"type":"element","tag":"span","props":{"class":"ct-288c45"},"children":[{"type":"text","value":"("}]},{"type":"element","tag":"span","props":{"class":"ct-da067e"},"children":[{"type":"text","value":"\"latam\""}]},{"type":"element","tag":"span","props":{"class":"ct-288c45"},"children":[{"type":"text","value":");"}]}]}]}]}]},{"type":"element","tag":"style","children":[{"type":"text","value":".ct-245334{color:#116329}\n.ct-37dcf1{color:#82071E}\n.ct-1f7ce8{color:#0550AE}\n.ct-81bc0b{color:#953800}\n.ct-8712d5{color:#CF222E}\n.ct-da067e{color:#0A3069}\n.ct-f604e1{color:#8250DF}\n.ct-288c45{color:#24292F}\n.ct-2c73f6{color:#6E7781}\n.dark .ct-2c73f6{color:#8B949E}\n.dark .ct-288c45{color:#C9D1D9}\n.dark .ct-f604e1{color:#D2A8FF}\n.dark .ct-da067e{color:#A5D6FF}\n.dark .ct-8712d5{color:#FF7B72}\n.dark .ct-81bc0b{color:#FFA657}\n.dark .ct-1f7ce8{color:#79C0FF}\n.dark .ct-37dcf1{color:#FFA198}\n.dark .ct-245334{color:#7EE787}"}]}],"toc":{"title":"","searchDepth":2,"depth":2,"links":[{"id":"leaguedivisionmapper","depth":2,"text":"LeagueDivisionMapper"},{"id":"leaguequeuemapper","depth":2,"text":"LeagueQueueMapper"},{"id":"leaguetiermapper","depth":2,"text":"LeagueTierMapper"},{"id":"lorregionmapper","depth":2,"text":"LorRegionMapper"},{"id":"tftleaguequeuemapper","depth":2,"text":"TftLeagueQueueMapper"},{"id":"platformmapper","depth":2,"text":"PlatformMapper"},{"id":"platformtoregionconverter","depth":2,"text":"PlatformToRegionConverter"},{"id":"prettyprinter","depth":2,"text":"PrettyPrinter"},{"id":"regionmapper","depth":2,"text":"RegionMapper"},{"id":"valregionmapper","depth":2,"text":"ValRegionMapper"}]}},"_type":"markdown","_id":"content:4.fundamentals:5.utilities.md","_source":"content","_file":"4.fundamentals/5.utilities.md","_extension":"md"}